feinsum/__init__.py
feinsum/canonicalization.py
feinsum/cl_utils.py
feinsum/diagnostics.py
feinsum/einsum.py
feinsum/loopy_utils.py
feinsum/make_einsum.py
feinsum/measure.py
feinsum/py.typed
feinsum/sql_utils.py
feinsum/typing.py
feinsum/utils.py
feinsum/codegen/__init__.py
feinsum/codegen/loopy.py
feinsum/data/__init__.py
feinsum/data/device_info.py
feinsum/data/transform_archive_v6.sqlite
feinsum/tuning/__init__.py
feinsum/tuning/impls/batched_xre_rij_ej_to_xei.py
feinsum/tuning/impls/batched_xre_rij_xej_to_ei.py
feinsum/tuning/impls/cogent.py
feinsum/tuning/impls/demo_transform_space.py
feinsum/tuning/impls/e_ij_ej_to_ei_no_prftch.py
feinsum/tuning/impls/ifj_fe_fej_to_ei.py
feinsum/tuning/impls/ij_ej_to_ei_no_prftch.py
feinsum/tuning/impls/ij_ij_to_ij.py
feinsum/tuning/impls/ij_j_to_i.py
feinsum/tuning/impls/ij_to_i.py
feinsum/tuning/impls/ijk_ijk_to_ijk.py
feinsum/tuning/impls/xre_rij_ej_to_xei.py
feinsum/tuning/impls/xre_rij_xej_to_ei.py
feinsum-2025.3.dist-info/METADATA
feinsum-2025.3.dist-info/WHEEL
feinsum-2025.3.dist-info/licenses/LICENSE.txt
feinsum-2025.3.dist-info/RECORD
