Metadata-Version: 2.4
Name: feinsum
Version: 2025.3
Summary: Fast(er?) Einsum
Project-URL: Homepage, https://github.com/kaushikcfd/feinsum/
Author-email: Kaushik Kulkarni <kaushikcfd@gmail.com>
License: The MIT License (MIT)
License-File: LICENSE.txt
Classifier: Development Status :: 4 - Beta
Classifier: Intended Audience :: Science/Research
Classifier: Programming Language :: Python :: 3
Classifier: Topic :: Scientific/Engineering
Classifier: Topic :: Scientific/Engineering :: Mathematics
Classifier: Topic :: Software Development :: Libraries
Requires-Python: >=3.12
Requires-Dist: bidict
Requires-Dist: immutables
Requires-Dist: islpy
Requires-Dist: loopy
Requires-Dist: more-itertools
Requires-Dist: numpy>=1.20
Requires-Dist: opentuner
Requires-Dist: opt-einsum
Requires-Dist: pybliss
Requires-Dist: pyopencl
Requires-Dist: pytools
Requires-Dist: pytz
Requires-Dist: tabulate
